texstrip/__init__.py
texstrip/__main__.py
texstrip/strip_comments.py
texstrip-0.1.1.dist-info/LICENSE
texstrip-0.1.1.dist-info/METADATA
texstrip-0.1.1.dist-info/WHEEL
texstrip-0.1.1.dist-info/entry_points.txt
texstrip-0.1.1.dist-info/top_level.txt
texstrip-0.1.1.dist-info/RECORD
