Metadata-Version: 2.1
Name: texstrip
Version: 0.1.1
Summary: strip comments from LaTeX sources.
Home-page: https://github.com/bl4ck5un/texstrip.py
Author: Fan Zhang
Author-email: bl4ck5unxx@gmail.com
License: MIT
Keywords: LaTeX
Platform: UNKNOWN
Classifier: Development Status :: 3 - Alpha
Classifier: Intended Audience :: End Users/Desktop
Classifier: Topic :: Utilities
Classifier: License :: OSI Approved :: MIT License
Classifier: Programming Language :: Python :: 3
Classifier: Programming Language :: Python :: 3.7
Requires-Dist: chromalog
Requires-Dist: docopt
Requires-Dist: ply
